setup.py
whippersnapper/__init__.py
whippersnapper/screenshotter.py
whippersnapper/target.py
whippersnapper/uploader.py
whippersnapper/whippersnapper.py
whippersnapper.egg-info/PKG-INFO
whippersnapper.egg-info/SOURCES.txt
whippersnapper.egg-info/dependency_links.txt
whippersnapper.egg-info/entry_points.txt
whippersnapper.egg-info/requires.txt
whippersnapper.egg-info/top_level.txt