Metadata-Version: 1.1
Name: whippersnapper
Version: 0.0.2
Summary: Whippersnapper is an automated screenshot tool to keep a visual history of content on the web.
Home-page: http://github.com/washingtonpost/whippersnapper
Author: Kevin Schaul, Katie Park
Author-email: kevin.schaul@washpost.com, katie.park@washpost.com
License: UNKNOWN
Platform: UNKNOWN
Classifier: Development Status :: 4 - Beta
Classifier: Environment :: Console
Classifier: Intended Audience :: Developers
Classifier: Natural Language :: English
Classifier: Operating System :: Unix
Classifier: Programming Language :: Python
